{
  "node": {
    "loaded": true,
    "valid": true,
    "id": "0x0000000f00000000000000000000000000000000000000000000000000000000",
    "prettyId": "0x0000000f",
    "image": "https://ipfs.io/ipfs/bafkreidcfpdxmks6er5haag2ahqtifrfva4oxwckd43kfp3mbempgpnz6y",
    "createdAt": null,
    "name": "WASD",
    "description": ""
  },
  "children": [
    {
      "node": {
        "loaded": true,
        "valid": true,
        "id": "0x0000000f00010000000000000000000000000000000000000000000000000000",
        "prettyId": "0x0000000f.0001",
        "image": "",
        "createdAt": null,
        "name": "Autonomous Admin",
        "description": "",
        "authorities": []
      },
      "children": [
        {
          "node": {
            "loaded": true,
            "valid": true,
            "id": "0x0000000f00010001000000000000000000000000000000000000000000000000",
            "prettyId": "0x0000000f.0001.0001",
            "image": "",
            "createdAt": null,
            "name": "Guild Leader",
            "description": "Leader of the WASD Guild",
            "authorities": [
              {
                "label": "Discord: Guild Leader",
                "description": "",
                "link": "https://discord.com/",
                "imageUrl": "",
                "gate": ""
              }
            ]
          },
          "children": [
            {
              "node": {
                "loaded": true,
                "valid": true,
                "id": "0x0000000f00010001000100000000000000000000000000000000000000000000",
                "prettyId": "0x0000000f.0001.0001.0001",
                "image": "",
                "createdAt": null,
                "name": "Level 1",
                "description": "No description",
                "authorities": []
              }
            },
            {
              "node": {
                "loaded": true,
                "valid": true,
                "id": "0x0000000f00010001000200000000000000000000000000000000000000000000",
                "prettyId": "0x0000000f.0001.0001.0002",
                "image": "",
                "createdAt": null,
                "name": "Level 2",
                "description": "No description",
                "authorities": []
              }
            },
            {
              "node": {
                "loaded": true,
                "valid": true,
                "id": "0x0000000f00010001000300000000000000000000000000000000000000000000",
                "prettyId": "0x0000000f.0001.0001.0003",
                "image": "https://ipfs.io/ipfs/bafkreickn3iiflfxqief2oy7haxuqea7j2hsxk4djrlllvlnqyqwstj3z4",
                "createdAt": null,
                "name": "Level 3",
                "description": "",
                "authorities": []
              }
            },
            {
              "node": {
                "loaded": true,
                "valid": true,
                "id": "0x0000000f00010001000400000000000000000000000000000000000000000000",
                "prettyId": "0x0000000f.0001.0001.0004",
                "image": "https://ipfs.io/ipfs/bafkreickn3iiflfxqief2oy7haxuqea7j2hsxk4djrlllvlnqyqwstj3z4",
                "createdAt": null,
                "name": "Level 3",
                "description": "",
                "authorities": []
              }
            }
          ]
        }
      ]
    }
  ]
}